README.md
setup.py
leppa/__init__.py
leppa/cl1.py
leppa/cl2.py
leppa.egg-info/PKG-INFO
leppa.egg-info/SOURCES.txt
leppa.egg-info/dependency_links.txt
leppa.egg-info/requires.txt
leppa.egg-info/top_level.txt