Metadata-Version: 2.1
Name: leppa
Version: 0.0.3
Summary: Leppa
Home-page: UNKNOWN
Author: Hrushikesh Kachgunde
Author-email: <hrushiskachgunde@gmail.com>
License: UNKNOWN
Keywords: python,neural networks,ann,prediction,ART neural network
Platform: UNKNOWN
Classifier: Development Status :: 1 - Planning
Classifier: Intended Audience :: Developers
Classifier: Programming Language :: Python :: 3
Classifier: Operating System :: Unix
Classifier: Operating System :: MacOS :: MacOS X
Classifier: Operating System :: Microsoft :: Windows
